nonebot_plugin_bot_poke/__init__.py
nonebot_plugin_bot_poke-0.1.0.dist-info/METADATA
nonebot_plugin_bot_poke-0.1.0.dist-info/WHEEL
nonebot_plugin_bot_poke-0.1.0.dist-info/RECORD
