Metadata-Version: 2.1
Name: nonebot_plugin_bot_poke
Version: 0.1.0
Summary: 人机合一戳别人
License: MIT
Author: Endless-Path
Author-email: rk.chensiyu@gmail.com
Requires-Python: >=3.8,<4.0
Classifier: License :: OSI Approved :: MIT License
Classifier: Programming Language :: Python :: 3
Classifier: Programming Language :: Python :: 3.8
Classifier: Programming Language :: Python :: 3.9
Classifier: Programming Language :: Python :: 3.10
Classifier: Programming Language :: Python :: 3.11
Classifier: Programming Language :: Python :: 3.12
Classifier: Programming Language :: Python :: 3.13
Requires-Dist: nonebot-adapter-onebot (>=2.2.0,<3.0.0)
Requires-Dist: nonebot2 (>=2.0.0,<3.0.0)
